hydrotools/events/baseflow/__init__.py
hydrotools/events/baseflow/eckhardt.py
hydrotools/events/event_detection/__init__.py
hydrotools/events/event_detection/_version.py
hydrotools/events/event_detection/decomposition.py
hydrotools/events/models/__init__.py
hydrotools/events/models/interception.py
hydrotools_events-2.2.0.dist-info/licenses/LICENSE
hydrotools_events-2.2.0.dist-info/licenses/NOTICE
hydrotools_events-2.2.0.dist-info/METADATA
hydrotools_events-2.2.0.dist-info/WHEEL
hydrotools_events-2.2.0.dist-info/top_level.txt
hydrotools_events-2.2.0.dist-info/RECORD
